{
  "project_info": {
    "project_number": "750377028145",
    "project_id": "momy-laundry-e587a",
    "storage_bucket": "momy-laundry-e587a.appspot.com"
  },
  "client": [
    {
      "client_info": {
        "mobilesdk_app_id": "1:750377028145:android:c201436f243d399776a310",
        "android_client_info": {
          "package_name": "com.laundary.laundary_system"
        }
      },
      "oauth_client": [
        {
          "client_id": "750377028145-4o0d2rfdtvpqosq8i7mjrerpnuub1f26.apps.googleusercontent.com",
          "client_type": 3
        }
      ],
      "api_key": [
        {
          "current_key": "AIzaSyBakgDeJiuU1N2aJcgY10dK6Q8RcNdv_zg"
        }
      ],
      "services": {
        "appinvite_service": {
          "other_platform_oauth_client": [
            {
              "client_id": "750377028145-4o0d2rfdtvpqosq8i7mjrerpnuub1f26.apps.googleusercontent.com",
              "client_type": 3
            }
          ]
        }
      }
    }
  ],
  "configuration_version": "1"
}